knowlify/LICENSE
knowlify/README.md
knowlify/__init__.py
knowlify/_api.py
knowlify/_auth.py
knowlify/_capture.py
knowlify/_config.py
knowlify/_prompt.py
knowlify/_utils.py
knowlify/_worker.py
knowlify/_ws.py
knowlify_ai-0.1.1.dist-info/METADATA
knowlify_ai-0.1.1.dist-info/WHEEL
knowlify_ai-0.1.1.dist-info/RECORD
