Metadata-Version: 2.4
Name: knowlify-ai
Version: 0.1.1
Summary: Turn your Python code into an explanatory video by calling knowlify.create('fast'|'detailed').
Project-URL: Homepage, https://knowlify.com
Author: Knowlify
License-Expression: MIT
Requires-Python: >=3.8
Requires-Dist: websockets>=12.0
